GWRExplain/__init__.py
GWRExplain/core/GWRExplain.py
GWRExplain/core/__init__.py
GWRExplain/core/geoshap.py
GWRExplain/core/spatial_weights.py
GWRExplain/preprocessing/__init__.py
GWRExplain/preprocessing/moran_test.py
GWRExplain/preprocessing/spatial_lag.py
GWRExplain/utils/__init__.py
GWRExplain/utils/metrics.py
GWRExplain/utils/parallel.py
GWRExplain/utils/search_neighbors.py
GWRExplain/visualization/__init__.py
GWRExplain/visualization/map_plot.py
GWRExplain-0.0.2.dist-info/LICENSE
GWRExplain-0.0.2.dist-info/METADATA
GWRExplain-0.0.2.dist-info/WHEEL
GWRExplain-0.0.2.dist-info/top_level.txt
GWRExplain-0.0.2.dist-info/RECORD
