Metadata-Version: 2.1
Name: GWRExplain
Version: 0.0.2
Summary: GWRExplain is a method that combines Geographically Weighted Regression (GWR) with explainability techniques to reveal how local variables influence prediction outcomes in spatial data.
Home-page: https://github.com/cbsux/GWRExplain
Author: ChiBeiSheng
Author-email: cbs3307821258@foxmail.com
Classifier: Programming Language :: Python :: 3
Classifier: License :: OSI Approved :: MIT License
Classifier: Operating System :: OS Independent
Requires-Python: >=3.10.0
License-File: LICENSE
Requires-Dist: numpy==2.2.5
Requires-Dist: pandas==2.2.3
Requires-Dist: matplotlib==3.10.1
Requires-Dist: scikit-learn==1.6.1
Requires-Dist: shap==0.47.2
